README.md
setup.py
license/__init__.py
license/cli.py
license/manager.py
license_cli.egg-info/PKG-INFO
license_cli.egg-info/SOURCES.txt
license_cli.egg-info/dependency_links.txt
license_cli.egg-info/entry_points.txt
license_cli.egg-info/not-zip-safe
license_cli.egg-info/requires.txt
license_cli.egg-info/top_level.txt