Metadata-Version: 2.1
Name: license-cli
Version: 1.0.1
Summary: Simple LICENSE.md generator.
Home-page: https://github.com/VoIlAlex/license-cli
Author: voilalex
Author-email: ilya.vouk@gmail.com
License: MIT
Download-URL: https://github.com/VoIlAlex/license-cli/archive/v1.0.1.tar.gz
Keywords: generator,opensource,license,LICENCE.md,cli
Platform: UNKNOWN
Classifier: Development Status :: 5 - Production/Stable
Classifier: Environment :: Console
Classifier: Topic :: Utilities
Classifier: Programming Language :: Python :: 3.5
Classifier: Programming Language :: Python :: 3.6
Classifier: Programming Language :: Python :: 3.7
Classifier: Programming Language :: Python :: 3.8
